README.md
pyproject.toml
setup.cfg
setup.py
cta/__init__.py
cta/client.py
cta/responses.py
cta/route.py
cta/stations.py
python_cta.egg-info/PKG-INFO
python_cta.egg-info/SOURCES.txt
python_cta.egg-info/dependency_links.txt
python_cta.egg-info/requires.txt
python_cta.egg-info/top_level.txt