Metadata-Version: 2.1
Name: python-cta
Version: 0.0.2
Summary: Python Client for Chicago Transit Data.
Home-page: https://github.com/wd60622/cta
Author: William Dean
Author-email: wd60622@gmail.com
Classifier: License :: OSI Approved :: MIT License
Classifier: Programming Language :: Python :: 3
Classifier: Programming Language :: Python :: 3.7
Classifier: Programming Language :: Python :: 3.8
Classifier: Programming Language :: Python :: 3.9
Classifier: Programming Language :: Python :: 3.10
